aturtle/__init__.py
aturtle/canvas.py
aturtle/turtle.py
aturtle/window.py
aturtle/shapes/__init__.py
aturtle/shapes/base.py
aturtle/shapes/bitmap.py
aturtle/shapes/vector.py
aturtle/sprites/__init__.py
aturtle/sprites/base.py
aturtle/sprites/bitmap.py
aturtle/sprites/vector.py
aturtle/utils/__init__.py
aturtle/utils/syncer.py
aturtle-1.0.0a0.dist-info/LICENSE
aturtle-1.0.0a0.dist-info/METADATA
aturtle-1.0.0a0.dist-info/WHEEL
aturtle-1.0.0a0.dist-info/top_level.txt
aturtle-1.0.0a0.dist-info/RECORD
