Metadata-Version: 2.1
Name: aturtle
Version: 1.0.0a0
Summary: Python A-Turtle
Home-page: https://github.com/tmontes/python-aturtle/
Author: Tiago Montes
Author-email: tiago.montes@gmail.com
Maintainer: Tiago Montes
Maintainer-email: tiago.montes@gmail.com
License: MIT
Keywords: functions,boilerplate
Platform: UNKNOWN
Classifier: Development Status :: 3 - Alpha
Classifier: Framework :: AsyncIO
Classifier: Intended Audience :: Developers
Classifier: Intended Audience :: Education
Classifier: License :: OSI Approved :: MIT License
Classifier: Natural Language :: English
Classifier: Operating System :: OS Independent
Classifier: Programming Language :: Python
Classifier: Programming Language :: Python :: 3
Classifier: Programming Language :: Python :: 3.8
Classifier: Topic :: Education
Classifier: Topic :: Games/Entertainment
Classifier: Topic :: Software Development :: Libraries :: Python Modules
Provides-Extra: dev
Requires-Dist: pillow ; extra == 'dev'
Requires-Dist: coverage ; extra == 'dev'
Requires-Dist: pylint ; extra == 'dev'
Requires-Dist: hypothesis ; extra == 'dev'
Provides-Extra: docs
Provides-Extra: pillow
Requires-Dist: pillow ; extra == 'pillow'
Provides-Extra: tests
Requires-Dist: coverage ; extra == 'tests'
Requires-Dist: pylint ; extra == 'tests'
Requires-Dist: hypothesis ; extra == 'tests'
